consys/__init__.py
consys/_db.py
consys/errors.py
consys/files.py
consys/handlers.py
consys/main.py
consys/model.py
consys/types.py
consys-0.43.dist-info/LICENSE
consys-0.43.dist-info/METADATA
consys-0.43.dist-info/WHEEL
consys-0.43.dist-info/top_level.txt
consys-0.43.dist-info/RECORD
