Metadata-Version: 2.1
Name: consys
Version: 0.43
Summary: Base object model for Python
Home-page: https://github.com/chilleco/consys
Author: Alex Poloz
Author-email: alexypoloz@gmail.com
License: MIT
Project-URL: Source, https://github.com/chilleco/consys
Keywords: base,object,model,oop,orm,python,mongodb,files,uploading,handlers,errors,types,checking
Classifier: Development Status :: 4 - Beta
Classifier: Environment :: Console
Classifier: Intended Audience :: Developers
Classifier: Topic :: Software Development :: Libraries :: Application Frameworks
Classifier: License :: OSI Approved :: MIT License
Classifier: Programming Language :: Python :: 3
Classifier: Operating System :: OS Independent
Requires-Python: >=3.7, <4
License-File: LICENSE
Requires-Dist: pymongo <5,>=4.10
Requires-Dist: pillow >=10
Requires-Dist: requests
Requires-Dist: pydantic <3,>=2.8
